cloudshell/__init__.py
cloudshell/sandbox_rest/__init__.py
cloudshell/sandbox_rest/exceptions.py
cloudshell/sandbox_rest/sandbox_api.py
cloudshell_sandbox_rest-0.1.1.dist-info/LICENSE
cloudshell_sandbox_rest-0.1.1.dist-info/METADATA
cloudshell_sandbox_rest-0.1.1.dist-info/WHEEL
cloudshell_sandbox_rest-0.1.1.dist-info/top_level.txt
cloudshell_sandbox_rest-0.1.1.dist-info/RECORD
