Metadata-Version: 2.1
Name: cloudshell-sandbox-rest
Version: 0.1.1
Summary: Python client for CloudShell Sandbox REST api - consume sandboxes via CI
Home-page: https://github.com/QualiSystemsLab/Sandbox-API-Python
Author: QualiLab
Author-email: support@qualisystems.com
License: MIT
Platform: UNKNOWN
Classifier: Programming Language :: Python :: 3.7
Classifier: License :: OSI Approved :: MIT License
Classifier: Operating System :: OS Independent
Requires-Python: >=3.7
License-File: LICENSE
Requires-Dist: requests (<3,>=2)
Requires-Dist: abstract-http-client (<2,>=1)
